djangolive/__init__.py
djangolive/manage.py
djangolive/apps/__init__.py
djangolive/apps/activeuser/__init__.py
djangolive/apps/activeuser/admin.py
djangolive/apps/activeuser/apps.py
djangolive/apps/activeuser/middleware.py
djangolive/apps/activeuser/models.py
djangolive/apps/activeuser/tests.py
djangolive/apps/activeuser/views.py
djangolive/apps/activeuser/migrations/0001_initial.py
djangolive/apps/activeuser/migrations/__init__.py
djangolive/core/__init__.py
djangolive/core/admin.py
djangolive/core/apps.py
djangolive/core/interfaces.py
djangolive/core/models.py
djangolive/core/tests.py
djangolive/core/utils.py
djangolive/core/views.py
djangolive/core/migrations/__init__.py
djangolive/djangolive/__init__.py
djangolive/djangolive/asgi.py
djangolive/djangolive/settings.py
djangolive/djangolive/urls.py
djangolive/djangolive/wsgi.py
djangolive/shared/__init__.py
djangolive/utils/__init__.py
djangolive/utils/_archive.py
djangolive/utils/profiler.py
djangolive-0.0.3.dist-info/LICENSE.txt
djangolive-0.0.3.dist-info/METADATA
djangolive-0.0.3.dist-info/WHEEL
djangolive-0.0.3.dist-info/top_level.txt
djangolive-0.0.3.dist-info/RECORD
